PyIntelligence/__init__.py
PyIntelligence/Supervised/__init__.py
PyIntelligence/Supervised/Classification/LogisticRegression.py
PyIntelligence/Supervised/Classification/__init__.py
PyIntelligence/Supervised/NeuralNetwork/Feedforward.py
PyIntelligence/Supervised/NeuralNetwork/__init__.py
PyIntelligence/Supervised/Regression/ElasticNet.py
PyIntelligence/Supervised/Regression/LassoRegression.py
PyIntelligence/Supervised/Regression/LinearRegression.py
PyIntelligence/Supervised/Regression/PolynomialRegression.py
PyIntelligence/Supervised/Regression/RidgeRegression.py
PyIntelligence/Supervised/Regression/__init__.py
pyintelligence-1.1.0.dist-info/licenses/LICENSE.txt
pyintelligence-1.1.0.dist-info/METADATA
pyintelligence-1.1.0.dist-info/WHEEL
pyintelligence-1.1.0.dist-info/top_level.txt
pyintelligence-1.1.0.dist-info/RECORD
