Metadata-Version: 2.4
Name: PyIntelligence
Version: 1.1.0
Summary: A light-weight and efficient modular machine learning library, designed for learning, experimenting and non-profit project!
Author: Vietthedev
License: MIT
Requires-Python: >=3.12
License-File: LICENSE.txt
Requires-Dist: numpy>=2.0.2
Dynamic: license-file
